owl_mcp/__init__.py
owl_mcp/axiom_parser.py
owl_mcp/config.py
owl_mcp/mcp_tools.py
owl_mcp/owl_api.py
owl_mcp/server.py
owl_mcp-0.1.2.dist-info/METADATA
owl_mcp-0.1.2.dist-info/WHEEL
owl_mcp-0.1.2.dist-info/entry_points.txt
owl_mcp-0.1.2.dist-info/RECORD
